rolling_king/__init__.py
rolling_king/autotest/__init__.py
rolling_king/autotest/db/__init__.py
rolling_king/autotest/db/db_models.py
rolling_king/autotest/db/db_util.py
rolling_king/autotest/db/sqlalchemy_util.py
rolling_king/autotest/requests/__init__.py
rolling_king/autotest/requests/http_sender_module.py
rolling_king/autotest/tests/__init__.py
rolling_king/autotest/tests/base/__init__.py
rolling_king/autotest/tests/base/autotest_generator.py
rolling_king/autotest/tests/base/base_compare.py
rolling_king/autotest/tests/base/base_conftest.py
rolling_king/autotest/tests/base/base_test.py
rolling_king/jason/__init__.py
rolling_king/jason/autogen/__init__.py
rolling_king/jason/autogen/auto_generate.py
rolling_king/jason/crawler/TempBaidu.py
rolling_king/jason/crawler/__init__.py
rolling_king/jason/crawler/crawler_urllib.py
rolling_king/jason/crawler/crawler_weibo.py
rolling_king/jason/newcore/__init__.py
rolling_king/jason/newcore/test_ccc.py
rolling_king/jason/openpyxl/__init__.py
rolling_king/jason/openpyxl/excel_util.py
rolling_king/jason/pypac/__init__.py
rolling_king/jason/pypac/pyfile1.py
rolling_king/jason/pypac/pyfile2.py
rolling_king/jason/pypac/test.py
rolling_king/jason/pytest/__init__.py
rolling_king/jason/pytest/conftest.py
rolling_king/jason/pytest/test_class.py
rolling_king/jason/pytest/test_sample.py
rolling_king/jason/python/ClassTest.py
rolling_king/jason/python/DbTest.py
rolling_king/jason/python/MailTest.py
rolling_king/jason/python/MyPyTest.py
rolling_king/jason/python/PythonTest.py
rolling_king/jason/python/QueueTest.py
rolling_king/jason/python/SeniorTest.py
rolling_king/jason/python/__init__.py
rolling_king/jason/python/socket/SocketClient.py
rolling_king/jason/python/socket/SocketServer.py
rolling_king/jason/python/socket/__init__.py
rolling_king/jason/python/thread/ThreadingTest.py
rolling_king/jason/python/thread/_ThreadTest.py
rolling_king/jason/python/thread/__init__.py
rolling_king/jason/python/tools/ExcelTest.py
cosco_shipping_autotest_framework-0.0.5.dist-info/LICENSE
cosco_shipping_autotest_framework-0.0.5.dist-info/METADATA
cosco_shipping_autotest_framework-0.0.5.dist-info/WHEEL
cosco_shipping_autotest_framework-0.0.5.dist-info/top_level.txt
cosco_shipping_autotest_framework-0.0.5.dist-info/RECORD
