Metadata-Version: 2.1
Name: cosco-shipping-autotest-framework
Version: 0.0.5
Summary: Python Project For QA Test
Home-page: https://gitee.com/jason024/python_project
Author: RollingKing
Author-email: 386773780@qq.com
Project-URL: Bug Tracker, https://gitee.com/jason024/python_project/issues
Classifier: Programming Language :: Python :: 3
Classifier: License :: OSI Approved :: MIT License
Classifier: Operating System :: OS Independent
Requires-Python: >=3.6
License-File: LICENSE
